LICENSE
MANIFEST.in
README.rst
setup.py
spamspy/__init__.py
spamspy/edit_dist.py
spamspy/ngram.py
spamspy/spamsum.py
spamspy.egg-info/PKG-INFO
spamspy.egg-info/SOURCES.txt
spamspy.egg-info/dependency_links.txt
spamspy.egg-info/entry_points.txt
spamspy.egg-info/top_level.txt