Metadata-Version: 1.0
Name: spamspy
Version: 0.1
Summary: UNKNOWN
Home-page: https://github.com/barahilia/spamspy
Author: Ilia Barahovsky
Author-email: barahilia@gmail.com
License: MIT License
Platform: UNKNOWN
